iterstring/__init__.py
iterstring/iterstring.py
iterstring-1.2.0.dist-info/LICENSE
iterstring-1.2.0.dist-info/WHEEL
iterstring-1.2.0.dist-info/METADATA
iterstring-1.2.0.dist-info/RECORD
